[
    {
        "title": "คอมพิวเตอร์คืออะไร",
        "subtitle": "คอมคือ เครื่องมือย่อโลก",
        "imges": "https://cdn.pixabay.com/photo/2015/01/08/18/25/desk-593327_1280.jpg",
        "detail": "เครื่องคำนวณอิเล็กทรอนิกส์โดยใช้วิธีทางคณิตศาสตร์ประกอบด้วยฮาร์ดแวร์ (ส่วนตัวเครื่องและอุปกรณ์) และซอฟต์แวร์ (ส่วนชุดคำสั่ง หรือโปรแกรมที่สั่งให้คอมพิวเตอร์ทำงาน) สามารถทำงานคำนวณผล และเปรียบเทียบค่าตามชุดคำสั่งด้วยความเร็วสูงอย่างต่อเนื่อง และอัตโนมัติ."
    },
    {
        "title": "มาเรียนกัน",
        "subtitle": "รักนะทุกคน",
        "imges": "https://cdn.pixabay.com/photo/2017/05/11/11/15/workplace-2303851_1280.jpg",
        "detail": "เป็นการนำผลลัพธ์จากการประมวลผลมาแสดงให้ทราบทางอุปกรณ์ที่กำหนดไว้ โดยทั่วไปจะแสดงผ่านทางจอภาพ หรือเรียกกันโดยทั่วไปว่า 'จอมอนิเตอร์' (Monitor) หรือจะพิมพ์ข้อมูล"
    },
    {
        "title": "flutter คืออะไร",
        "subtitle": "สิ่งที่กำลังเรียน",
        "imges": "https://cdn.pixabay.com/photo/2014/05/02/21/47/laptop-336369_1280.jpg",
        "detail": "คอมพิวเตอร์มาจากภาษาละตินว่า Computare ซึ่งหมายถึง การนับ หรือ การคำนวณ พจนานุกรม ฉบับราชบัณฑิตยสถาน พ.ศ. 2525 ให้ความหมายของคอมพิวเตอร์ไว้ว่า 'เครื่อง'"
    }
]